LICENSE
MANIFEST.in
README.md
pyproject.toml
setup.py
doc/CONTRIBUTING.md
doc/DEVELOPER.md
doc/api/INDEX.md
doc/api/constants.md
doc/api/diagnose.md
doc/api/get_max_contacts.md
doc/api/initialize.md
doc/api/inject.md
doc/api/is_available.md
doc/api/is_initialized.md
src/_wintouch/module.c
tests/__init__.py
tests/conftest.py
tests/test_availability.py
tests/test_constants.py
tests/test_initialize.py
tests/test_inject.py
tests/test_integration.py
wintouch/__init__.py
wintouch/py.typed
wintouch.egg-info/PKG-INFO
wintouch.egg-info/SOURCES.txt
wintouch.egg-info/dependency_links.txt
wintouch.egg-info/requires.txt
wintouch.egg-info/top_level.txt