Metadata-Version: 2.4
Name: wintouch
Version: 0.1.0
Summary: Windows Touch Injection API for Python
Author-email: Philip Dye <phdye@acm.org>
License-Expression: MIT
Project-URL: Homepage, https://github.com/phdye/wintouch
Project-URL: Documentation, https://github.com/phdye/wintouch/tree/main/doc
Project-URL: Repository, https://github.com/phdye/wintouch
Project-URL: Issues, https://github.com/phdye/wintouch/issues
Keywords: touch,injection,windows,input,simulation,testing,win32
Classifier: Development Status :: 3 - Alpha
Classifier: Environment :: Win32 (MS Windows)
Classifier: Intended Audience :: Developers
Classifier: Operating System :: Microsoft :: Windows
Classifier: Programming Language :: C
Classifier: Programming Language :: Python :: 3
Classifier: Programming Language :: Python :: 3.8
Classifier: Programming Language :: Python :: 3.9
Classifier: Programming Language :: Python :: 3.10
Classifier: Programming Language :: Python :: 3.11
Classifier: Programming Language :: Python :: 3.12
Classifier: Programming Language :: Python :: 3.13
Classifier: Programming Language :: Python :: 3.14
Classifier: Topic :: Software Development :: Testing
Classifier: Topic :: Software Development :: Libraries :: Python Modules
Classifier: Typing :: Typed
Requires-Python: >=3.8
License-File: LICENSE
Provides-Extra: dev
Requires-Dist: pytest>=7.0; extra == "dev"
Requires-Dist: black>=23.0; extra == "dev"
Requires-Dist: mypy>=1.0; extra == "dev"
Dynamic: license-file
